MANIFEST.in
Makefile
NonlinearLeastSquares-2.0.2.html
README
setup.py
ExamplesOptimizedSurfaceFit/README
ExamplesOptimizedSurfaceFit/grad_descent.py
ExamplesOptimizedSurfaceFit/grad_descent_with_partial_derivatives.py
ExamplesOptimizedSurfaceFit/leven_marq.py
ExamplesOptimizedSurfaceFit/leven_marq_with_partial_derivatives.py
ExamplesStructureFromCameraMotion/README
ExamplesStructureFromCameraMotion/bundle_adjust_sfm_with_uncalibrated_cameras_translations_only.py
ExamplesStructureFromCameraMotion/flyby_photos_of_3D_planar_shape.py
ExamplesStructureFromCameraMotion/sfm_with_calibrated_cameras_translations_only.py
ExamplesStructureFromCameraMotion/sfm_with_uncalibrated_cameras_translations_only.py
ExamplesStructureFromCameraMotion/take_photo_of_3D_planar_shape.py
ExamplesStructureFromCameraMotion/take_photo_of_virtual_cuboid.py
NonlinearLeastSquares/NonlinearLeastSquares.py
NonlinearLeastSquares/__init__.py
NonlinearLeastSquares.egg-info/PKG-INFO
NonlinearLeastSquares.egg-info/SOURCES.txt
NonlinearLeastSquares.egg-info/dependency_links.txt
NonlinearLeastSquares.egg-info/top_level.txt
OptimizedSurfaceFit/OptimizedSurfaceFit.py
OptimizedSurfaceFit/__init__.py
ProjectiveCamera/ProjectiveCamera.py
ProjectiveCamera/__init__.py
TestNonlinearLeastSquares/NonlinearLeastSquares.py
TestNonlinearLeastSquares/OptimizedSurfaceFit.py
TestNonlinearLeastSquares/Test.py
TestNonlinearLeastSquares/TestNonlinearLeastSquaresCalculation.py