Metadata-Version: 1.2
Name: NonlinearLeastSquares
Version: 2.0.2
Summary: A Python module for solving optimization problems with nonlinear least-squares
Home-page: https://engineering.purdue.edu/kak/distNonlinearLeastSquares/NonlinearLeastSquares-2.0.2.html
Author: Avinash Kak
Author-email: kak@purdue.edu
Maintainer: Avinash Kak
Maintainer-email: kak@purdue.edu
License: Python Software Foundation License
Download-URL: https://engineering.purdue.edu/kak/distNonlinearLeastSquares/NonlinearLeastSquares-2.0.2.tar.gz
Keywords: gradient descent,nonlinear least-squares,optimization,bundle adjustment
Platform: All platforms
Classifier: Topic :: Scientific/Engineering :: Information Analysis
Classifier: Programming Language :: Python :: 3.8
